Workbook
Name EndingCash: 'Cash Flow'!$B$37:$M$37
Name NetChangeInCash: 'Cash Flow'!$B$35:$M$35

Sheet Cash Flow
A1: Statement of Cash Flows
A2: Client
A3: Fiscal year
A4: Books closed through
A5: Source
A7: Fiscal month | B7: Jan | C7: Feb | D7: Mar | E7: Apr | F7: May | G7: Jun | H7: Jul | I7: Aug | J7: Sep | K7: Oct | L7: Nov | M7: Dec | N7: Year to date
A8: Cash flows from operating activities
A9: Net income | N9: =SUM(B9:M9) -> 0
A10: Adjustments to reconcile net income to net cash from operating activities:
A11: Depreciation and amortization | N11: =SUM(B11:M11) -> 0
A12: (Increase) decrease in accounts receivable | N12: =SUM(B12:M12) -> 0
A13: (Increase) decrease in inventory | N13: =SUM(B13:M13) -> 0
A14: (Increase) decrease in prepaid expenses and other current assets | N14: =SUM(B14:M14) -> 0
A15: Increase (decrease) in accounts payable | N15: =SUM(B15:M15) -> 0
A16: Increase (decrease) in credit cards payable | N16: =SUM(B16:M16) -> 0
A17: Increase (decrease) in accrued payroll and payroll taxes | N17: =SUM(B17:M17) -> 0
A18: Increase (decrease) in sales tax payable | N18: =SUM(B18:M18) -> 0
A19: Increase (decrease) in deferred revenue | N19: =SUM(B19:M19) -> 0
A20: Increase (decrease) in other current liabilities | N20: =SUM(B20:M20) -> 0
A21: Net cash provided by (used in) operating activities | B21: =SUM(B9:B20) -> 0 | C21: =SUM(C9:C20) -> 0 | D21: =SUM(D9:D20) -> 0 | E21: =SUM(E9:E20) -> 0 | F21: =SUM(F9:F20) -> 0 | G21: =SUM(G9:G20) -> 0 | H21: =SUM(H9:H20) -> 0 | I21: =SUM(I9:I20) -> 0 | ... N21: =SUM(N9:N20) -> 0
A23: Cash flows from investing activities
A24: Purchases of property and equipment | N24: =SUM(B24:M24) -> 0
A25: Other investing activities | N25: =SUM(B25:M25) -> 0
A26: Net cash provided by (used in) investing activities | B26: =SUM(B24:B25) -> 0 | C26: =SUM(C24:C25) -> 0 | D26: =SUM(D24:D25) -> 0 | E26: =SUM(E24:E25) -> 0 | F26: =SUM(F24:F25) -> 0 | G26: =SUM(G24:G25) -> 0 | H26: =SUM(H24:H25) -> 0 | I26: =SUM(I24:I25) -> 0 | ... N26: =SUM(N24:N25) -> 0
A28: Cash flows from financing activities
A29: Proceeds from (repayments of) loans, net | N29: =SUM(B29:M29) -> 0
A30: Borrowings (repayments) on line of credit, net | N30: =SUM(B30:M30) -> 0
A31: Owner contributions | N31: =SUM(B31:M31) -> 0
A32: Owner distributions | N32: =SUM(B32:M32) -> 0
A33: Net cash provided by (used in) financing activities | B33: =SUM(B29:B32) -> 0 | C33: =SUM(C29:C32) -> 0 | D33: =SUM(D29:D32) -> 0 | E33: =SUM(E29:E32) -> 0 | F33: =SUM(F29:F32) -> 0 | G33: =SUM(G29:G32) -> 0 | H33: =SUM(H29:H32) -> 0 | I33: =SUM(I29:I32) -> 0 | ... N33: =SUM(N29:N32) -> 0
A35: Net increase (decrease) in cash | B35: =B21+B26+B33 -> 0 | C35: =C21+C26+C33 -> 0 | D35: =D21+D26+D33 -> 0 | E35: =E21+E26+E33 -> 0 | F35: =F21+F26+F33 -> 0 | G35: =G21+G26+G33 -> 0 | H35: =H21+H26+H33 -> 0 | I35: =I21+I26+I33 -> 0 | ... N35: =N21+N26+N33 -> 0
A36: Cash at beginning of period | C36: =B37 -> 0 | D36: =C37 -> 0 | E36: =D37 -> 0 | F36: =E37 -> 0 | G36: =F37 -> 0 | H36: =G37 -> 0 | I36: =H37 -> 0 | J36: =I37 -> 0 | ... M36: =L37 -> 0 | N36: =B36 -> 0
A37: Cash at end of period | B37: =B36+B35 -> 0 | C37: =C36+C35 -> 0 | D37: =D36+D35 -> 0 | E37: =E36+E35 -> 0 | F37: =F36+F35 -> 0 | G37: =G36+G35 -> 0 | H37: =H36+H35 -> 0 | I37: =I36+I35 -> 0 | ... N37: =N36+N35 -> 0
A39: Cash per balance sheet
A40: Difference | B40: =IF(B39="","",ROUND(B37-B39,2)) -> 0 | C40: =IF(C39="","",ROUND(C37-C39,2)) -> 0 | D40: =IF(D39="","",ROUND(D37-D39,2)) -> 0 | E40: =IF(E39="","",ROUND(E37-E39,2)) -> 0 | F40: =IF(F39="","",ROUND(F37-F39,2)) -> 0 | G40: =IF(G39="","",ROUND(G37-G39,2)) -> 0 | H40: =IF(H39="","",ROUND(H37-H39,2)) -> 0 | I40: =IF(I39="","",ROUND(I37-I39,2)) -> 0 | ... M40: =IF(M39="","",ROUND(M37-M39,2)) -> 0
A42: Reviewed by
A43: Review date

Sheet Summary
A1: Cash summary
A2: ='Cash Flow'!B2 -> 0
A3: ="Fiscal year "&'Cash Flow'!B3 -> 0
A5: Month | B5: Operating | C5: Investing | D5: Financing | E5: Net change | F5: Ending cash
A6: Jan | B6: ='Cash Flow'!B21 -> 0 | C6: ='Cash Flow'!B26 -> 0 | D6: ='Cash Flow'!B33 -> 0 | E6: ='Cash Flow'!B35 -> 0 | F6: =IF('Cash Flow'!B39="",NA(),'Cash Flow'!B37) -> 0
A7: Feb | B7: ='Cash Flow'!C21 -> 0 | C7: ='Cash Flow'!C26 -> 0 | D7: ='Cash Flow'!C33 -> 0 | E7: ='Cash Flow'!C35 -> 0 | F7: =IF('Cash Flow'!C39="",NA(),'Cash Flow'!C37) -> 0
A8: Mar | B8: ='Cash Flow'!D21 -> 0 | C8: ='Cash Flow'!D26 -> 0 | D8: ='Cash Flow'!D33 -> 0 | E8: ='Cash Flow'!D35 -> 0 | F8: =IF('Cash Flow'!D39="",NA(),'Cash Flow'!D37) -> 0
A9: Apr | B9: ='Cash Flow'!E21 -> 0 | C9: ='Cash Flow'!E26 -> 0 | D9: ='Cash Flow'!E33 -> 0 | E9: ='Cash Flow'!E35 -> 0 | F9: =IF('Cash Flow'!E39="",NA(),'Cash Flow'!E37) -> 0
A10: May | B10: ='Cash Flow'!F21 -> 0 | C10: ='Cash Flow'!F26 -> 0 | D10: ='Cash Flow'!F33 -> 0 | E10: ='Cash Flow'!F35 -> 0 | F10: =IF('Cash Flow'!F39="",NA(),'Cash Flow'!F37) -> 0
A11: Jun | B11: ='Cash Flow'!G21 -> 0 | C11: ='Cash Flow'!G26 -> 0 | D11: ='Cash Flow'!G33 -> 0 | E11: ='Cash Flow'!G35 -> 0 | F11: =IF('Cash Flow'!G39="",NA(),'Cash Flow'!G37) -> 0
A12: Jul | B12: ='Cash Flow'!H21 -> 0 | C12: ='Cash Flow'!H26 -> 0 | D12: ='Cash Flow'!H33 -> 0 | E12: ='Cash Flow'!H35 -> 0 | F12: =IF('Cash Flow'!H39="",NA(),'Cash Flow'!H37) -> 0
A13: Aug | B13: ='Cash Flow'!I21 -> 0 | C13: ='Cash Flow'!I26 -> 0 | D13: ='Cash Flow'!I33 -> 0 | E13: ='Cash Flow'!I35 -> 0 | F13: =IF('Cash Flow'!I39="",NA(),'Cash Flow'!I37) -> 0
A14: Sep | B14: ='Cash Flow'!J21 -> 0 | C14: ='Cash Flow'!J26 -> 0 | D14: ='Cash Flow'!J33 -> 0 | E14: ='Cash Flow'!J35 -> 0 | F14: =IF('Cash Flow'!J39="",NA(),'Cash Flow'!J37) -> 0
A15: Oct | B15: ='Cash Flow'!K21 -> 0 | C15: ='Cash Flow'!K26 -> 0 | D15: ='Cash Flow'!K33 -> 0 | E15: ='Cash Flow'!K35 -> 0 | F15: =IF('Cash Flow'!K39="",NA(),'Cash Flow'!K37) -> 0
A16: Nov | B16: ='Cash Flow'!L21 -> 0 | C16: ='Cash Flow'!L26 -> 0 | D16: ='Cash Flow'!L33 -> 0 | E16: ='Cash Flow'!L35 -> 0 | F16: =IF('Cash Flow'!L39="",NA(),'Cash Flow'!L37) -> 0
A17: Dec | B17: ='Cash Flow'!M21 -> 0 | C17: ='Cash Flow'!M26 -> 0 | D17: ='Cash Flow'!M33 -> 0 | E17: ='Cash Flow'!M35 -> 0 | F17: =IF('Cash Flow'!M39="",NA(),'Cash Flow'!M37) -> 0
A18: Total | B18: =SUM(B6:B17) -> 0 | C18: =SUM(C6:C17) -> 0 | D18: =SUM(D6:D17) -> 0 | E18: =SUM(E6:E17) -> 0

Sheet Lists
A1: MQ
A2: DH
A3: TN
